camorph/__init__.py
camorph/__main__.py
camorph/camorph.py
camorph/cli.py
camorph/conf.py
camorph/ext/__init__.py
camorph/ext/COLMAP/COLMAP.py
camorph/ext/COLMAP/__init__.py
camorph/ext/COLMAP/model/CameraModel.py
camorph/ext/COLMAP/model/ColmapCamera.py
camorph/ext/COLMAP/model/ColmapImage.py
camorph/ext/COLMAP/model/__init__.py
camorph/ext/COLMAP/util/ReaderSyntacticUtil.py
camorph/ext/COLMAP/util/WriterSyntacticUtil.py
camorph/ext/COLMAP/util/__init__.py
camorph/ext/FBX/FBX.py
camorph/ext/FBX/__init__.py
camorph/ext/FBX/model/FBXConnection.py
camorph/ext/FBX/model/FBXHierachyNode.py
camorph/ext/FBX/model/FBXNode.py
camorph/ext/FBX/model/FBXNodeObject.py
camorph/ext/FBX/model/FBXPrimitiveValues.py
camorph/ext/FBX/model/FBXProperty.py
camorph/ext/FBX/model/__init__.py
camorph/ext/FBX/util/ReaderSemanticUtil.py
camorph/ext/FBX/util/ReaderSyntacticUtil.py
camorph/ext/FBX/util/WriterSyntacticUtil.py
camorph/ext/FBX/util/__init__.py
camorph/ext/LLFF/LLFF.py
camorph/ext/LLFF/__init__.py
camorph/ext/MPEG_OMAF/MPEG_OMAF.py
camorph/ext/MPEG_OMAF/__init__.py
camorph/ext/Meshroom/Mehsroom.py
camorph/ext/Meshroom/__init__.py
camorph/ext/Meshroom/model/__init__.py
camorph/ext/Meshroom/model/sfm.py
camorph/ext/Meshroom/util/ReaderSyntacticUtil.py
camorph/ext/Meshroom/util/WriterSyntacticUtil.py
camorph/ext/Meshroom/util/__init__.py
camorph/ext/NeRF/NeRF.py
camorph/ext/NeRF/__init__.py
camorph/ext/RealityCapture/RealityCapture.py
camorph/ext/RealityCapture/__init__.py
camorph/ext/Unity/Unity.py
camorph/ext/Unity/__init__.py
camorph/ext/Unity/model/UnityCamera.py
camorph/ext/Unity/model/UnityGameObject.py
camorph/ext/Unity/model/UnityTransform.py
camorph/ext/Unity/model/__init__.py
camorph/ext/Unity/util/ReaderSemanticUtil.py
camorph/ext/Unity/util/ReaderSyntacticUtil.py
camorph/ext/Unity/util/WriterSyntacticUtil.py
camorph/ext/Unity/util/__init__.py
camorph/lib/__init__.py
camorph/lib/crucial_property.py
camorph/lib/visualizer.py
camorph/lib/model/Camera.py
camorph-1.0.0.dist-info/licenses/LICENSE.txt
camorph-1.0.0.dist-info/METADATA
camorph-1.0.0.dist-info/WHEEL
camorph-1.0.0.dist-info/entry_points.txt
camorph-1.0.0.dist-info/top_level.txt
camorph-1.0.0.dist-info/RECORD
