Metadata-Version: 2.4
Name: camorph
Version: 1.0.0
Summary: Camorph is a python library for converting different camera parameter representations into each other
Author-email: Benjamin Brand <BenniBrand@gmx.de>
License: The Clear BSD License
Project-URL: Homepage, https://github.com/Fraunhofer-IIS/camorph
Keywords: camera parameter convention,conversion
Classifier: Programming Language :: Python :: 3
Requires-Python: >=3.9
License-File: LICENSE.txt
Requires-Dist: matplotlib>=3.5.0
Requires-Dist: numpy>=1.21.2
Requires-Dist: Pillow>=9.2.0
Requires-Dist: pyquaternion>=0.9.9
Requires-Dist: PyYAML>=6.0
Requires-Dist: rdflib>=6.1.1
Dynamic: license-file
